mooyoUtils/__init__.py
mooyoUtils/handlerEmail.py
mooyoUtils/handlerMysql.py
mooyoUtils/handlerRedis.py
mooyoUtils/logger.py
mooyoUtils/pyapollo.py
mooyoUtils/read_config.py
mooyoUtils/utilFileTrans.py
mooyoUtils/utilFtp.py
mooyoUtils/utilGPG.py
mooyoUtils/utilSftp.py
mooyoUtils/utilXXLJob.py
mooyoUtils/utilXls.py
mooyoUtils/utilZipfile.py
mooyoUtils/wechatRobot.py
mooyoUtils-1.0.0.dist-info/COPYING.txt
mooyoUtils-1.0.0.dist-info/METADATA
mooyoUtils-1.0.0.dist-info/WHEEL
mooyoUtils-1.0.0.dist-info/top_level.txt
mooyoUtils-1.0.0.dist-info/RECORD
