Metadata-Version: 2.1
Name: mooyoUtils
Version: 1.0.0
Summary: mooyo 常用工具包
Home-page: http://git.ppdaicorp.com/chenqiang08/mooyoUtils.git
Author: Jackie Chen
Author-email: mooyo@live.cn
Maintainer: Jackie Chen
Maintainer-email: mooyo@live.cn
License: MIT
Platform: all
Classifier: Development Status :: 4 - Beta
Classifier: Operating System :: OS Independent
Classifier: Intended Audience :: Developers
Classifier: License :: OSI Approved :: BSD License
Classifier: Programming Language :: Python
Classifier: Programming Language :: Python :: Implementation
Classifier: Programming Language :: Python :: 2
Classifier: Programming Language :: Python :: 2.7
Classifier: Programming Language :: Python :: 3
Classifier: Programming Language :: Python :: 3.4
Classifier: Programming Language :: Python :: 3.5
Classifier: Programming Language :: Python :: 3.6
Classifier: Topic :: Software Development :: Libraries
License-File: COPYING.txt
Requires-Dist: portion
Requires-Dist: demjson
Requires-Dist: python-dateutil
Requires-Dist: paramiko
Requires-Dist: redis
Requires-Dist: jsonpath
Requires-Dist: pymysql
Requires-Dist: apscheduler
Requires-Dist: requests
Requires-Dist: gnupg
Requires-Dist: xlrd
